examples/__init__.py
examples/generic_graph.py
examples/json_graph.py
examples/static_graph.py
typed_graph/__init__.py
typed_graph/dependency_traits.py
typed_graph/generic_graph.py
typed_graph/partial_typed_graph.py
typed_graph/typed_error.py
typed_graph/typed_graph.py
typed_graph/typed_traits.py
typed_graph-0.4.0.dist-info/LICENSE
typed_graph-0.4.0.dist-info/METADATA
typed_graph-0.4.0.dist-info/WHEEL
typed_graph-0.4.0.dist-info/top_level.txt
typed_graph-0.4.0.dist-info/RECORD
