Metadata-Version: 2.1
Name: typed-graph
Version: 0.4.0
Summary: Staticly typed graph library
Home-page: https://github.com/build-aau/typed_graph
Author: lcabyg
Author-email: lcabyg@build.aau.dk
License: Apache Software License v2.0
Keywords: graph,type
Platform: UNKNOWN
Classifier: Programming Language :: Python :: 3.10
Classifier: Programming Language :: Python :: 3.11
Classifier: License :: OSI Approved :: Apache Software License
Classifier: Operating System :: OS Independent
Requires-Python: >=3.10
License-File: LICENSE
Requires-Dist: pydantic ~=2.5
Requires-Dist: typing ~=3.7
